LICENSE
MANIFEST.in
README.rst
helga_dubstep.py
setup.py
helga_dubstep.egg-info/PKG-INFO
helga_dubstep.egg-info/SOURCES.txt
helga_dubstep.egg-info/dependency_links.txt
helga_dubstep.egg-info/entry_points.txt
helga_dubstep.egg-info/top_level.txt
helga_dubstep.egg-info/zip-safe